eon_fms_client/__init__.py
eon_fms_client-0.2.3.dist-info/METADATA
eon_fms_client-0.2.3.dist-info/WHEEL
eon_fms_client-0.2.3.dist-info/top_level.txt
eon_fms_client-0.2.3.dist-info/RECORD
