Metadata-Version: 2.1
Name: eon-fms-client
Version: 0.2.3
Home-page: https://bitbucket.org/eon-mes/broker_utilities/src/master
Author: Ahmad Salameh
Author-email: a.salameh@eonaligner.com
License: MIT
Keywords: eon fms client
Requires-Dist: python-magic (==0.4.27)
Requires-Dist: requests (==2.25.1)
